ocr_hooks/__init__.py
ocr_hooks/_pyinstaller.py
ocr_hooks/hooks/hook-ddddocr.py
ocr_hooks/hooks/hook-onnxruntime.py
ocr_hooks-2025.8.4.1.dist-info/WHEEL
ocr_hooks-2025.8.4.1.dist-info/entry_points.txt
ocr_hooks-2025.8.4.1.dist-info/METADATA
ocr_hooks-2025.8.4.1.dist-info/RECORD
