Metadata-Version: 2.3
Name: ocr-hooks
Version: 2025.8.4.1
Summary: pyinstaller hooks for ddddocr and onnxruntime
Author: Maple
Author-email: Maple <wjxa20152015@gmail.com>
Requires-Dist: ddddocr>=1.3.6
Requires-Dist: onnxruntime==1.20.0
Requires-Dist: pyinstaller>=6.2.0
Requires-Python: >=3.12
